flask_sawtooth/__init__.py
flask_sawtooth/exceptions.py
flask_sawtooth/sawtooth.py
Flask_Sawtooth-0.3.0.dist-info/LICENSE
Flask_Sawtooth-0.3.0.dist-info/METADATA
Flask_Sawtooth-0.3.0.dist-info/WHEEL
Flask_Sawtooth-0.3.0.dist-info/top_level.txt
Flask_Sawtooth-0.3.0.dist-info/RECORD
