Metadata-Version: 2.1
Name: Flask-Sawtooth
Version: 0.3.0
Summary: A Sawtooth utlity library as a Flask extension.
Home-page: https://github.com/MakeCents-NYC/flask-sawtooth
Author: Thomas Veale, Bo Yao
Author-email: tveale@mymakecents.com, byao@mymakecents.com
License: GPLv2
Platform: any
Classifier: Environment :: Web Environment
Classifier: Intended Audience :: Developers
Classifier: License :: OSI Approved :: GNU General Public License v2 (GPLv2)
Classifier: Operating System :: OS Independent
Classifier: Programming Language :: Python
Classifier: Topic :: Software Development :: Libraries :: Python Modules
Requires-Dist: Flask
Requires-Dist: sawtooth-sdk (<1.1,>=1.0)
Requires-Dist: sawtooth-signing (<1.1,>=1.0)
Requires-Dist: requests
Requires-Dist: cbor2
Requires-Dist: pyzmq
